acru_l/__init__.py
acru_l/apps/__init__.py
acru_l/apps/base.py
acru_l/resources/__init__.py
acru_l/resources/apigateway.py
acru_l/resources/canary/__init__.py
acru_l/resources/canary/resource.py
acru_l/resources/canary/src/handler.py
acru_l/resources/canary/src/requirements.txt
acru_l/resources/custom_resources.py
acru_l/resources/dynamodb.py
acru_l/resources/functions.py
acru_l/resources/hosted_zone.py
acru_l/resources/rds/__init__.py
acru_l/resources/rds/instances.py
acru_l/resources/rds/serverless.py
acru_l/resources/ses/__init__.py
acru_l/resources/ses/domain_validation/__init__.py
acru_l/resources/ses/domain_validation/handler.py
acru_l/resources/ses/layer/requirements.txt
acru_l/resources/ses/verfication.py
acru_l/resources/ses/verified_emails/__init__.py
acru_l/resources/ses/verified_emails/handler.py
acru_l/resources/vpc.py
acru_l/services/__init__.py
acru_l/services/asgi.py
acru_l/services/base.py
acru_l/services/node.py
acru_l/services/wsgi/__init__.py
acru_l/services/wsgi/service.py
acru_l/services/wsgi/src/handler.py
acru_l/services/wsgi/src/requirements.txt
acru_l/stacks/__init__.py
acru_l/stacks/base.py
acru_l/stacks/certs.py
acru_l/stacks/config.py
acru_l/stacks/lucario.py
acru_l/stacks/network.py
acru_l/stacks/ses.py
acru_l-0.1.4.dist-info/LICENSE
acru_l-0.1.4.dist-info/WHEEL
acru_l-0.1.4.dist-info/METADATA
acru_l-0.1.4.dist-info/RECORD
